Workbook

Sheet KPI Dashboard
A1: CAVA GROUP | FY2025 PERFORMANCE & FY2026 OUTLOOK | P1: Metric | Q1: ='Quarterly Trend'!B3 -> Q1 2025 16 Weeks | R1: ='Quarterly Trend'!C3 -> Q2 2025 12 Weeks | S1: ='Quarterly Trend'!D3 -> Q3 2025 12 Weeks | T1: ='Quarterly Trend'!E3 -> Q4 2025 12 Weeks
P2: Revenue | Q2: ='Quarterly Trend'!B4 -> 331826 | R2: ='Quarterly Trend'!C4 -> 280615 | S2: ='Quarterly Trend'!D4 -> 292238 | T2: ='Quarterly Trend'!E4 -> 274985
A3: $ in thousands except percentages, points, and restaurant counts | P3: Margin % | Q3: ='Quarterly Trend'!B5 -> 0.251 | R3: ='Quarterly Trend'!C5 -> 0.263 | S3: ='Quarterly Trend'!D5 -> 0.246 | T3: ='Quarterly Trend'!E5 -> 0.214
I4: Actual | K4: Guidance-derived | M4: Modeled assumption | P4: Adjusted EBITDA | Q4: ='Quarterly Trend'!B6 -> 44850 | R4: ='Quarterly Trend'!C6 -> 42100 | S4: ='Quarterly Trend'!D6 -> 40000 | T4: ='Quarterly Trend'!E6 -> 25764
A5: REVENUE | F5: RESTAURANT-LEVEL MARGIN | K5: ADJUSTED EBITDA
A7: ='FY25 Actuals'!F5 -> 1179664 | C7: ='FY26 RL Forecast'!F4 -> 1325738.1 | F7: ='FY25 Actuals'!F12 -> 0.24377612 | H7: ='FY26 RL Forecast'!F13 -> 0.23978187 | K7: ='Guidance vs Actual'!E8 -> 152760 | M7: ='FY26 RL Assumptions'!C22 -> 180000
A10: FY2025 Actual | C10: FY2026 Base Forecast | F10: FY2025 Actual | H10: FY2026 Bottom-Up Forecast | K10: FY2025 Actual | M10: FY2026 Guidance Midpoint
A12: FY2025 QUARTERLY TREND | I12: FY2025 GUIDANCE VS. ACTUAL
A13: Metric | B13: Q1 2025 16 Weeks | C13: Q2 2025 12 Weeks | D13: Q3 2025 12 Weeks | E13: Q4 2025 12 Weeks | F13: Status | I13: Metric | J13: Guidance | K13: Actual | L13: Variance | M13: Unit | N13: Status
A14: Revenue | B14: ='Quarterly Trend'!B4 -> 331826 | C14: ='Quarterly Trend'!C4 -> 280615 | D14: ='Quarterly Trend'!D4 -> 292238 | E14: ='Quarterly Trend'!E4 -> 274985 | F14: Actual | I14: Net New Openings | J14: =TEXT('Guidance vs Actual'!B4,"0")&"–"&TEXT('Guidance vs Actual'!D4,"0") -> 62–66 | K14: ='Guidance vs Actual'!E4 -> 72 | L14: ='Guidance vs Actual'!H4 -> 6 | M14: restaurants | N14: Guidance / Actual
A15: Restaurant-Level Margin % | B15: ='Quarterly Trend'!B5 -> 0.251 | C15: ='Quarterly Trend'!C5 -> 0.263 | D15: ='Quarterly Trend'!D5 -> 0.246 | E15: ='Quarterly Trend'!E5 -> 0.214 | F15: Actual | I15: Same-Restaurant Sales Growth | J15: =TEXT('Guidance vs Actual'!B5,"0.0%")&"–"&TEXT('Guidance vs Actual'!D5,"0.0%") -> 6.0%–8.0% | K15: ='Guidance vs Actual'!E5 -> 0.04 | L15: ='Guidance vs Actual'!G5 -> -0.03 | M15: pts | N15: Guidance / Actual
A16: Adjusted EBITDA | B16: ='Quarterly Trend'!B6 -> 44850 | C16: ='Quarterly Trend'!C6 -> 42100 | D16: ='Quarterly Trend'!D6 -> 40000 | E16: ='Quarterly Trend'!E6 -> 25764 | F16: Actual | I16: Restaurant-Level Margin | J16: =TEXT('Guidance vs Actual'!B6,"0.0%")&"–"&TEXT('Guidance vs Actual'!D6,"0.0%") -> 24.8%–25.2% | K16: ='Guidance vs Actual'!E6 -> 0.244 | L16: ='Guidance vs Actual'!G6 -> -0.006 | M16: pts | N16: Guidance / Actual
I17: Pre-opening Costs | J17: =TEXT('Guidance vs Actual'!B7/1000,"$0.0")&"M–"&TEXT('Guidance vs Actual'!D7/1000,"$0.0")&"M" -> $14.0M–$15.0M | K17: ='Guidance vs Actual'!E7 -> 19134 | L17: ='Guidance vs Actual'!G7 -> 4634 | M17: $000s | N17: Guidance / Actual
I18: Adjusted EBITDA | J18: =TEXT('Guidance vs Actual'!B8/1000,"$0.0")&"M–"&TEXT('Guidance vs Actual'!D8/1000,"$0.0")&"M" -> $150.0M–$157.0M | K18: ='Guidance vs Actual'!E8 -> 152760 | L18: ='Guidance vs Actual'!G8 -> -740 | M18: $000s | N18: Guidance / Actual
A30: FY2025 ACTUALS & FY2026 BASE FORECAST BUILD
A31: Metric | B31: Q1 FY2025 | C31: Q2 FY2025 | D31: Q3 FY2025 | E31: Q4 FY2025 | F31: FY2025 Actual | H31: Q1 FY2026 | I31: Q2 FY2026 | J31: Q3 FY2026 | K31: Q4 FY2026 | L31: FY2026 Base | M31: Classification | N31: Traceability
A32: Revenue | B32: ='Quarterly Trend'!B4 -> 331826 | C32: ='Quarterly Trend'!C4 -> 280615 | D32: ='Quarterly Trend'!D4 -> 292238 | E32: ='Quarterly Trend'!E4 -> 274985 | F32: ='FY25 Actuals'!F5 -> 1179664 | H32: ='FY26 RL Forecast'!B4 -> 372914.96 | I32: ='FY26 RL Forecast'!C4 -> 315362.67 | J32: ='FY26 RL Forecast'!D4 -> 328424.91 | K32: ='FY26 RL Forecast'!E4 -> 309035.52 | L32: ='FY26 RL Forecast'!F4 -> 1325738.1 | M32: Actual / Modeled | N32: FY2025 actual; FY2026 modeled base
A33: COGS | B33: ='FY25 Actuals'!B7 -> 96224 | C33: ='FY25 Actuals'!C7 -> 82210 | D33: ='FY25 Actuals'!D7 -> 87245 | E33: ='FY25 Actuals'!E7 -> 83005 | F33: ='FY25 Actuals'!F7 -> 348684 | H33: ='FY26 RL Forecast'!B6 -> 110731.65 | I33: ='FY26 RL Forecast'!C6 -> 94436.862 | J33: ='FY26 RL Forecast'!D6 -> 100191.26 | K33: ='FY26 RL Forecast'!E6 -> 95277.575 | L33: ='FY26 RL Forecast'!F6 -> 400637.34 | M33: Actual / Modeled | N33: FY2026 quarterly COGS trend build
A34: Labor | B34: ='FY25 Actuals'!B9 -> 84562 | C34: ='FY25 Actuals'!C9 -> 69496 | D34: ='FY25 Actuals'!D9 -> 73849 | E34: ='FY25 Actuals'!E9 -> 73954 | F34: ='FY25 Actuals'!F9 -> 301861 | H34: ='FY26 RL Forecast'!B8 -> 96000.497 | I34: ='FY26 RL Forecast'!C8 -> 78765.58 | J34: ='FY26 RL Forecast'!D8 -> 83695.442 | K34: ='FY26 RL Forecast'!E8 -> 83787.002 | L34: ='FY26 RL Forecast'!F8 -> 342248.52 | M34: Actual / Modeled | N34: FY2026 quarterly Labor trend build
A35: Restaurant-Level Profit | B35: ='FY25 Actuals'!B11 -> 82305 | C35: ='FY25 Actuals'!C11 -> 73262 | D35: ='FY25 Actuals'!D11 -> 71165 | E35: ='FY25 Actuals'!E11 -> 58312 | F35: ='FY25 Actuals'!F11 -> 285044 | H35: ='FY26 RL Forecast'!B12 -> 91946.538 | I35: ='FY26 RL Forecast'!C12 -> 81772.45 | J35: ='FY26 RL Forecast'!D12 -> 79339.879 | K35: ='FY26 RL Forecast'!E12 -> 64829.083 | L35: ='FY26 RL Forecast'!F12 -> 317887.95 | M35: Actual / Guidance-derived | N35: FY2026 bottom-up restaurant-level profit
A36: Restaurant-Level Margin % | B36: ='FY25 Actuals'!B12 -> 0.25056167 | C36: ='FY25 Actuals'!C12 -> 0.26329654 | D36: ='FY25 Actuals'!D12 -> 0.24557692 | E36: ='FY25 Actuals'!E12 -> 0.21377874 | F36: ='FY25 Actuals'!F12 -> 0.24377612 | H36: ='FY26 RL Forecast'!B13 -> 0.24656167 | I36: ='FY26 RL Forecast'!C13 -> 0.25929654 | J36: ='FY26 RL Forecast'!D13 -> 0.24157692 | K36: ='FY26 RL Forecast'!E13 -> 0.20977874 | L36: ='FY26 RL Forecast'!F13 -> 0.23978187 | M36: Actual / Guidance-derived | N36: FY2026 bottom-up restaurant-level margin
A39: SOURCE STATUS: FY2025 actuals verified | FY2025 original guidance verified | FY2026 outlook uses CAVA guidance and existing modeled assumptions only
A40: Primary sources: CAVA Q4 FY2024 earnings release (FY2025 guidance); CAVA Q1–Q4 FY2025 earnings releases and FY2025 Form 10-K; FY2026 base forecast model established in this project.

Sheet Guidance vs Actual
A1: CAVA Group — FY2025 Original Guidance vs. Actual
A3: Metric | B3: Guidance Low | C3: Guidance Midpoint | D3: Guidance High | E3: FY2025 Actual | F3: Variance vs Low | G3: Variance vs Midpoint | H3: Variance vs High | I3: Variance Unit | J3: Guidance Status | K3: Actual Status | L3: Guidance Source | M3: Actual Source
A4: Net New CAVA Restaurant Openings | B4: 62 | C4: 64 | D4: 66 | E4: 72 | F4: =E4-B4 -> 10 | G4: =E4-C4 -> 8 | H4: =E4-D4 -> 6 | I4: restaurants | J4: Verified — Feb. 25, 2025 guidance | K4: Verified — FY2025 actual | L4: https://investor.cava.com/news/news-details/2025/CAVA-Group-Reports-Fourth-Quarter-and-Full-Year-Fiscal-2024-Results/default.aspx | M4: https://investor.cava.com/news/news-details/2026/CAVA-Group-Reports-Fourth-Quarter-and-Full-Year-Fiscal-2025-Results/default.aspx
A5: Same-Restaurant Sales Growth | B5: 0.06 | C5: 0.07 | D5: 0.08 | E5: 0.04 | F5: =E5-B5 -> -0.02 | G5: =E5-C5 -> -0.03 | H5: =E5-D5 -> -0.04 | I5: percentage points | J5: Verified — Feb. 25, 2025 guidance | K5: Verified — FY2025 actual | L5: https://investor.cava.com/news/news-details/2025/CAVA-Group-Reports-Fourth-Quarter-and-Full-Year-Fiscal-2024-Results/default.aspx | M5: https://investor.cava.com/news/news-details/2026/CAVA-Group-Reports-Fourth-Quarter-and-Full-Year-Fiscal-2025-Results/default.aspx
A6: CAVA Restaurant-Level Profit Margin | B6: 0.248 | C6: 0.25 | D6: 0.252 | E6: 0.244 | F6: =E6-B6 -> -0.004 | G6: =E6-C6 -> -0.006 | H6: =E6-D6 -> -0.008 | I6: percentage points | J6: Verified — Feb. 25, 2025 guidance | K6: Verified — FY2025 actual | L6: https://investor.cava.com/news/news-details/2025/CAVA-Group-Reports-Fourth-Quarter-and-Full-Year-Fiscal-2024-Results/default.aspx | M6: https://investor.cava.com/news/news-details/2026/CAVA-Group-Reports-Fourth-Quarter-and-Full-Year-Fiscal-2025-Results/default.aspx
A7: Pre-opening Costs ($000s) | B7: 14000 | C7: 14500 | D7: 15000 | E7: 19134 | F7: =E7-B7 -> 5134 | G7: =E7-C7 -> 4634 | H7: =E7-D7 -> 4134 | I7: $000s | J7: Verified — Feb. 25, 2025 guidance | K7: Verified — FY2025 actual | L7: https://investor.cava.com/news/news-details/2025/CAVA-Group-Reports-Fourth-Quarter-and-Full-Year-Fiscal-2024-Results/default.aspx | M7: https://investor.cava.com/news/news-details/2026/CAVA-Group-Reports-Fourth-Quarter-and-Full-Year-Fiscal-2025-Results/default.aspx
A8: Adjusted EBITDA ($000s) | B8: 150000 | C8: 153500 | D8: 157000 | E8: 152760 | F8: =E8-B8 -> 2760 | G8: =E8-C8 -> -740 | H8: =E8-D8 -> -4240 | I8: $000s | J8: Verified — Feb. 25, 2025 guidance | K8: Verified — FY2025 actual | L8: https://investor.cava.com/news/news-details/2025/CAVA-Group-Reports-Fourth-Quarter-and-Full-Year-Fiscal-2024-Results/default.aspx | M8: https://investor.cava.com/news/news-details/2026/CAVA-Group-Reports-Fourth-Quarter-and-Full-Year-Fiscal-2025-Results/default.aspx

Sheet Quarterly Trend
A1: CAVA Group — FY2025 Quarterly Trend
A3: Metric | B3: Q1 2025 16 Weeks | C3: Q2 2025 12 Weeks | D3: Q3 2025 12 Weeks | E3: Q4 2025 12 Weeks | F3: Verification Status | G3: Primary Source | H3: Units | J3: Metric | K3: Q1 2025 | L3: Q2 2025 | M3: Q3 2025 | N3: Q4 2025
A4: Revenue | B4: 331826 | C4: 280615 | D4: 292238 | E4: 274985 | F4: Verified — primary-source quarterly statements | G4: Q1: https://investor.cava.com/news/news-details/2025/CAVA-Group-Reports-First-Quarter-2025-Results/default.aspx | Q2: https://investor.cava.com/news/news-details/2025/CAVA-Group-Reports-Second-Quarter-2025-Results/default.aspx | Q3: https://investor.cava.com/news/news-details/2025/CAVA-Group-Reports-Third-Quarter-2025-Results/default.aspx | Q4: https://investor.cava.com/news/news-details/2026/CAVA-Group-Reports-Fourth-Quarter-and-Full-Year-Fiscal-2025-Results/default.aspx | H4: $000s | J4: Revenue | K4: 331826 | L4: 280615 | M4: 292238 | N4: 274985
A5: Restaurant-Level Margin % | B5: 0.251 | C5: 0.263 | D5: 0.246 | E5: 0.214 | F5: Verified — primary-source earnings releases | G5: Q1: https://investor.cava.com/news/news-details/2025/CAVA-Group-Reports-First-Quarter-2025-Results/default.aspx | Q2: https://investor.cava.com/news/news-details/2025/CAVA-Group-Reports-Second-Quarter-2025-Results/default.aspx | Q3: https://investor.cava.com/news/news-details/2025/CAVA-Group-Reports-Third-Quarter-2025-Results/default.aspx | Q4: https://investor.cava.com/news/news-details/2026/CAVA-Group-Reports-Fourth-Quarter-and-Full-Year-Fiscal-2025-Results/default.aspx | H5: % | J5: Adjusted EBITDA | K5: 44850 | L5: 42100 | M5: 40000 | N5: 25764
A6: Adjusted EBITDA | B6: 44850 | C6: 42100 | D6: 40000 | E6: 25764 | F6: Verified — primary-source earnings releases | G6: Q1: https://investor.cava.com/news/news-details/2025/CAVA-Group-Reports-First-Quarter-2025-Results/default.aspx | Q2: https://investor.cava.com/news/news-details/2025/CAVA-Group-Reports-Second-Quarter-2025-Results/default.aspx | Q3: https://investor.cava.com/news/news-details/2025/CAVA-Group-Reports-Third-Quarter-2025-Results/default.aspx | Q4: https://investor.cava.com/news/news-details/2026/CAVA-Group-Reports-Fourth-Quarter-and-Full-Year-Fiscal-2025-Results/default.aspx | H6: $000s | J6: Restaurant-Level Margin % | K6: 0.251 | L6: 0.263 | M6: 0.246 | N6: 0.214

Sheet FY25 Actuals
A1: FY2025 Actual Baseline
A3: Financial Metric | B3: Q1 2025 16 Weeks | C3: Q2 2025 12 Weeks | D3: Q3 2025 12 Weeks | E3: Q4 2025 12 Weeks | F3: FY2025 52 Weeks | G3: Data Status | H3: Source / Filing | I3: Validation Status | J3: Analyst Note
A4: Weeks in Period | B4: 16 | C4: 12 | D4: 12 | E4: 12 | F4: 52 | G4: Actual | H4: FY2025 fiscal calendar | I4: Provided
A5: Total Revenue | B5: 331826 | C5: 280615 | D5: 292238 | E5: 274985 | F5: =SUM(B5:E5) -> 1179664 | G5: Actual | H5: User-provided verified dataset | I5: Verified | J5: Q1–Q4 and FY2025 total provided directly by user.
A6: CAVA Restaurant Revenue | B6: 328482 | C6: 278249 | D6: 289787 | E6: 272768 | F6: =SUM(B6:E6) -> 1169286 | G6: Actual | H6: FY2025 Form 10-K / earnings releases | I6: Provided
A7: Food, Beverage & Packaging (COGS) $ | B7: 96224 | C7: 82210 | D7: 87245 | E7: 83005 | F7: =SUM(B7:E7) -> 348684 | G7: Actual | H7: User-provided verified dataset | I7: Verified | J7: Q1 $97,559K; Q2 $82,950K; Q3 $88,289K; Q4 $83,980K; FY $352,778K.
A8: Food, Beverage & Packaging (COGS) % | B8: =B7/B6 -> 0.29293538 | C8: =C7/C6 -> 0.29545479 | D8: =D7/D6 -> 0.30106596 | E8: =E7/E6 -> 0.30430622 | F8: =F7/F6 -> 0.29820249 | G8: Actual | H8: User-provided verified dataset | I8: Verified | J8: Q1 29.4%; Q2 29.6%; Q3 30.2%; Q4 30.5%; FY 29.9%.
A9: Labor & Related Costs $ | B9: 84562 | C9: 69496 | D9: 73849 | E9: 73954 | F9: =SUM(B9:E9) -> 301861 | G9: Actual | H9: User-provided verified dataset | I9: Verified | J9: Q1 $84,562K; Q2 $69,496K; Q3 $73,849K; Q4 $73,954K; FY $301,861K.
A10: Labor & Related Costs % | B10: =B9/B6 -> 0.25743268 | C10: =C9/C6 -> 0.2497619 | D10: =D9/D6 -> 0.2548389 | E10: =E9/E6 -> 0.27112418 | F10: =F9/F6 -> 0.2581584 | G10: Actual | H10: User-provided verified dataset | I10: Verified | J10: Q1 25.5%; Q2 24.8%; Q3 25.3%; Q4 26.9%; FY 25.6%.
A11: Restaurant-Level Profit $ | B11: 82305 | C11: 73262 | D11: 71165 | E11: 58312 | F11: =SUM(B11:E11) -> 285044 | G11: Actual | H11: FY2025 earnings releases | I11: Provided
A12: Restaurant-Level Margin % | B12: =B11/B6 -> 0.25056167 | C12: =C11/C6 -> 0.26329654 | D12: =D11/D6 -> 0.24557692 | E12: =E11/E6 -> 0.21377874 | F12: =F11/F6 -> 0.24377612 | G12: Actual | H12: FY2025 earnings releases | I12: Provided
A13: General & Administrative (G&A) | B13: 41394 | C13: 32051 | D13: 31499 | E13: 32518 | F13: =SUM(B13:E13) -> 137462 | G13: Actual / supplied | H13: CAVA Q4/FY2025 earnings release (Form 8-K, Ex. 99.1), Consolidated Statements of Operations. | I13: Verified | J13: Q4 corrected from $32,500K to $32,518K per primary source; FY total $137,462K.
A14: Depreciation & Amortization (D&A) | B14: 20811 | C14: 16815 | D14: 17628 | E14: 18407 | F14: =SUM(B14:E14) -> 73661 | G14: Actual | H14: CAVA Q2 2025 Form 10-Q / FY2025 Form 10-K, Statements of Cash Flows. | I14: Verified | J14: Q1 $20,811K; Q2 $16,815K; Q3 $17,628K; Q4 $18,407K; FY $73,661K.
A15: Pre-opening Costs | B15: 4481 | C15: 5096 | D15: 4942 | E15: 4615 | F15: =SUM(B15:E15) -> 19134 | G15: Actual | H15: User-provided verified dataset | I15: Verified | J15: Q1–Q4 and FY2025 total provided directly by user.
A16: AUV ($000s) | B16: 2933 | C16: 2939 | D16: 2935 | E16: 2934 | F16: 2930 | G16: Actual | H16: CAVA Q4/FY2025 earnings release (Form 8-K, Ex. 99.1), Selected Quarterly Financial and Other Data table. | I16: Verified | J16: Q1 $2,933K; Q2 $2,939K; Q3 $2,935K; Q4 $2,934K (trailing-thirteen-period basis, per footnote 1); FY $2,930K.
A17: Same Restaurant Sales % | B17: 0.108 | C17: 0.021 | D17: 0.019 | E17: 0.005 | F17: 0.04 | G17: Actual | H17: User-provided verified dataset | I17: Verified
A18: Digital Mix % | B18: 0.38 | C18: 0.373 | D18: 0.376 | E18: 0.389 | F18: 0.379 | G18: Actual | H18: CAVA Q1-Q4 2025 quarterly earnings releases (Form 8-K, Ex. 99.1 each quarter). | I18: Verified | J18: Q1 38.0%; Q2 37.3%; Q3 37.6%; Q4 38.9%; FY 37.9% (revenue-weighted; confirmed against quarterly revenue).

Sheet FY26 RL Assumptions
A1: CAVA Group — FY2026 Restaurant-Level Forecast Assumptions
A3: Driver / Assumption | B3: Q1 FY2025 | C3: Q2 FY2025 | D3: Q3 FY2025 | E3: Q4 FY2025 | F3: FY2025 / Guidance | G3: FY2026 Q1 | H3: FY2026 Q2 | I3: FY2026 Q3 | J3: FY2026 Q4
A4: Revenue ($000s) | B4: ='FY25 Actuals'!B5 -> 331826 | C4: ='FY25 Actuals'!C5 -> 280615 | D4: ='FY25 Actuals'!D5 -> 292238 | E4: ='FY25 Actuals'!E5 -> 274985 | F4: ='FY25 Actuals'!F5 -> 1179664
A5: Revenue Seasonality | B5: =B4/$F$4 -> 0.28128857 | C5: =C4/$F$4 -> 0.23787706 | D5: =D4/$F$4 -> 0.24772986 | E5: =E4/$F$4 -> 0.23310451 | F5: =SUM(B5:E5) -> 1 | G5: =B5 -> 0.28128857 | H5: =C5 -> 0.23787706 | I5: =D5 -> 0.24772986 | J5: =E5 -> 0.23310451
A6: AUV ($000s) | B6: ='FY25 Actuals'!B16 -> 2933 | C6: ='FY25 Actuals'!C16 -> 2939 | D6: ='FY25 Actuals'!D16 -> 2935 | E6: =IF('FY25 Actuals'!E16="","",'FY25 Actuals'!E16) -> 2934 | F6: ='FY25 Actuals'!F16 -> 2930
A7: COGS % | B7: ='FY25 Actuals'!B8 -> 0.29293538 | C7: ='FY25 Actuals'!C8 -> 0.29545479 | D7: ='FY25 Actuals'!D8 -> 0.30106596 | E7: ='FY25 Actuals'!E8 -> 0.30430622 | F7: ='FY25 Actuals'!F8 -> 0.29820249 | G7: =B7+$C$25 -> 0.29693538 | H7: =C7+$C$25 -> 0.29945479 | I7: =D7+$C$25 -> 0.30506596 | J7: =E7+$C$25 -> 0.30830622
A8: Labor % | B8: ='FY25 Actuals'!B10 -> 0.25743268 | C8: ='FY25 Actuals'!C10 -> 0.2497619 | D8: ='FY25 Actuals'!D10 -> 0.2548389 | E8: ='FY25 Actuals'!E10 -> 0.27112418 | F8: ='FY25 Actuals'!F10 -> 0.2581584 | G8: =B8 -> 0.25743268 | H8: =C8 -> 0.2497619 | I8: =D8 -> 0.2548389 | J8: =E8 -> 0.27112418
A9: Pre-opening Costs ($000s) | B9: ='FY25 Actuals'!B15 -> 4481 | C9: ='FY25 Actuals'!C15 -> 5096 | D9: ='FY25 Actuals'!D15 -> 4942 | E9: ='FY25 Actuals'!E15 -> 4615 | F9: ='FY25 Actuals'!F15 -> 19134
A10: Restaurant-Level Margin % | B10: ='FY25 Actuals'!B12 -> 0.25056167 | C10: ='FY25 Actuals'!C12 -> 0.26329654 | D10: ='FY25 Actuals'!D12 -> 0.24557692 | E10: ='FY25 Actuals'!E12 -> 0.21377874 | F10: ='FY25 Actuals'!F12 -> 0.24377612
A11: Same Restaurant Sales % | B11: ='FY25 Actuals'!B17 -> 0.108 | C11: ='FY25 Actuals'!C17 -> 0.021 | D11: ='FY25 Actuals'!D17 -> 0.019 | E11: ='FY25 Actuals'!E17 -> 0.005 | F11: ='FY25 Actuals'!F17 -> 0.04
A12: Digital Mix % | B12: =IF('FY25 Actuals'!B18="","",'FY25 Actuals'!B18) -> 0.38 | C12: =IF('FY25 Actuals'!C18="","",'FY25 Actuals'!C18) -> 0.373 | D12: =IF('FY25 Actuals'!D18="","",'FY25 Actuals'!D18) -> 0.376 | E12: ='FY25 Actuals'!E18 -> 0.389 | F12: ='FY25 Actuals'!F18 -> 0.379
A13: Occupancy / Other OPEX % | B13: =1-B7-B8-B10 -> 0.19907027 | C13: =1-C7-C8-C10 -> 0.19148676 | D13: =1-D7-D8-D10 -> 0.19851822 | E13: =1-E7-E8-E10 -> 0.21079086 | F13: =SUMPRODUCT(B5:E5,B13:E13) -> 0.19986169 | G13: =B13 -> 0.19907027 | H13: =C13 -> 0.19148676 | I13: =D13 -> 0.19851822 | J13: =E13 -> 0.21079086
A14: COGS ($000s) | B14: ='FY25 Actuals'!B7 -> 96224 | C14: ='FY25 Actuals'!C7 -> 82210 | D14: ='FY25 Actuals'!D7 -> 87245 | E14: ='FY25 Actuals'!E7 -> 83005 | F14: ='FY25 Actuals'!F7 -> 348684
A15: Labor ($000s) | B15: ='FY25 Actuals'!B9 -> 84562 | C15: ='FY25 Actuals'!C9 -> 69496 | D15: ='FY25 Actuals'!D9 -> 73849 | E15: ='FY25 Actuals'!E9 -> 73954 | F15: ='FY25 Actuals'!F9 -> 301861
A16: FY2026 Guidance and Explicit Model Assumptions
A17: Input | B17: Low | C17: Base | D17: High | E17: Unit | F17: Classification / Traceability | H17: Revenue Build Formula
A18: Net New Openings | B18: 74 | C18: 75 | D18: 76 | E18: restaurants | F18: Management guidance | H18: FY2025 Revenue × (1 + Same Restaurant Sales midpoint) + Net New Openings midpoint × FY2025 AUV × Average-Year Contribution × New Restaurant Productivity
A19: Same Restaurant Sales | B19: 0.03 | C19: 0.04 | D19: 0.05 | E19: % | F19: Management guidance
A20: Restaurant-Level Margin | B20: 0.237 | C20: 0.2395 | D20: 0.242 | E20: % | F20: Management guidance
A21: Pre-opening Costs | B21: 19500 | C21: 19750 | D21: 20000 | E21: $000s | F21: Management guidance
A22: Adjusted EBITDA | B22: 176000 | C22: 180000 | D22: 184000 | E22: $000s | F22: Management guidance
A23: Average-Year Contribution of New Openings | B23: 0.5 | C23: 0.5 | D23: 0.5 | E23: year-equivalent | F23: Modeled assumption — midpoint opening timing | H23: Classification Legend
A24: New Restaurant Revenue vs. AUV | B24: 0.9 | C24: 0.9 | D24: 0.9 | E24: x | F24: Modeled assumption — first-year productivity | H24: Verified Actual | I24: Blue font | J24: Provided verified dataset
A25: COGS Trend Overlay | B25: 0.004 | C25: 0.004 | D25: 0.004 | E25: pts | F25: Modeled assumption — +0.4 pts vs. each FY2025 quarter | H25: Guidance-derived | I25: Green fill | J25: Management forward-looking guidance
A26: Labor Trend Overlay | B26: 0 | C26: 0 | D26: 0 | E26: pts | F26: Modeled assumption — FY2025 quarterly pattern held | H26: Modeled Assumption | I26: Yellow fill | J26: Requires human review
A27: Occupancy / Other OPEX Overlay | B27: 0 | C27: 0 | D27: 0 | E27: pts | F27: Modeled assumption — FY2025 quarterly pattern held

Sheet FY26 RL Forecast
A1: CAVA Group — FY2026 Restaurant-Level P&L Forecast
A3: Financial Metric | B3: Q1 FY2026 16 Weeks | C3: Q2 FY2026 12 Weeks | D3: Q3 FY2026 12 Weeks | E3: Q4 FY2026 12 Weeks | F3: FY2026 52 Weeks | G3: Classification | H3: Traceability / Assumption
A4: Revenue | B4: =$F4*'FY26 RL Assumptions'!G5 -> 372914.96 | C4: =$F4*'FY26 RL Assumptions'!H5 -> 315362.67 | D4: =$F4*'FY26 RL Assumptions'!I5 -> 328424.91 | E4: =$F4*'FY26 RL Assumptions'!J5 -> 309035.52 | F4: ='FY26 RL Assumptions'!F4*(1+'FY26 RL Assumptions'!C19)+'FY26 RL Assumptions'!C18*'FY26 RL Assumptions'!F6*'FY26 RL Assumptions'!C23*'FY26 RL Assumptions'!C24 -> 1325738.1 | G4: Modeled assumption | H4: FY2025 revenue + SRS midpoint + net-new unit contribution
A5: Revenue Growth % | B5: =B4/'FY26 RL Assumptions'!B4-1 -> 0.12382684 | C5: =C4/'FY26 RL Assumptions'!C4-1 -> 0.12382684 | D5: =D4/'FY26 RL Assumptions'!D4-1 -> 0.12382684 | E5: =E4/'FY26 RL Assumptions'!E4-1 -> 0.12382684 | F5: =F4/'FY26 RL Assumptions'!F4-1 -> 0.12382684 | G5: Modeled calculation | H5: FY2026 quarter vs. FY2025 verified quarter
A6: COGS | B6: =B4*B7 -> 110731.65 | C6: =C4*C7 -> 94436.862 | D6: =D4*D7 -> 100191.26 | E6: =E4*E7 -> 95277.575 | F6: =SUM(B6:E6) -> 400637.34 | G6: Modeled calculation | H6: Revenue × quarterly COGS %
A7: COGS % | B7: ='FY26 RL Assumptions'!G7 -> 0.29693538 | C7: ='FY26 RL Assumptions'!H7 -> 0.29945479 | D7: ='FY26 RL Assumptions'!I7 -> 0.30506596 | E7: ='FY26 RL Assumptions'!J7 -> 0.30830622 | F7: =F6/F4 -> 0.30219947 | G7: Modeled assumption | H7: FY2025 quarterly COGS % + 0.4 pts
A8: Labor | B8: =B4*B9 -> 96000.497 | C8: =C4*C9 -> 78765.58 | D8: =D4*D9 -> 83695.442 | E8: =E4*E9 -> 83787.002 | F8: =SUM(B8:E8) -> 342248.52 | G8: Modeled calculation | H8: Revenue × quarterly Labor %
A9: Labor % | B9: ='FY26 RL Assumptions'!G8 -> 0.25743268 | C9: ='FY26 RL Assumptions'!H8 -> 0.2497619 | D9: ='FY26 RL Assumptions'!I8 -> 0.2548389 | E9: ='FY26 RL Assumptions'!J8 -> 0.27112418 | F9: =F8/F4 -> 0.25815697 | G9: Modeled assumption | H9: FY2025 quarterly Labor % held
A10: Occupancy / Other OPEX | B10: =B4*B11 -> 74236.282 | C10: =C4*C11 -> 60387.776 | D10: =D4*D11 -> 65198.329 | E10: =E4*E11 -> 65141.862 | F10: =SUM(B10:E10) -> 264964.25 | G10: Modeled calculation | H10: Revenue × quarterly Occupancy/OPEX %
A11: Occupancy / Other OPEX % | B11: ='FY26 RL Assumptions'!G13 -> 0.19907027 | C11: ='FY26 RL Assumptions'!H13 -> 0.19148676 | D11: ='FY26 RL Assumptions'!I13 -> 0.19851822 | E11: ='FY26 RL Assumptions'!J13 -> 0.21079086 | F11: =F10/F4 -> 0.19986169 | G11: Modeled assumption | H11: FY2025 quarterly residual held
A12: Restaurant-Level Profit | B12: =B4-B6-B8-B10 -> 91946.538 | C12: =C4-C6-C8-C10 -> 81772.45 | D12: =D4-D6-D8-D10 -> 79339.879 | E12: =E4-E6-E8-E10 -> 64829.083 | F12: =SUM(B12:E12) -> 317887.95 | G12: Modeled calculation | H12: Revenue less COGS, Labor, Occupancy/OPEX
A13: Restaurant-Level Margin % | B13: =B12/B4 -> 0.24656167 | C13: =C12/C4 -> 0.25929654 | D13: =D12/D4 -> 0.24157692 | E13: =E12/E4 -> 0.20977874 | F13: =F12/F4 -> 0.23978187 | G13: Modeled calculation | H13: Bottom-up margin
A14: Pre-opening Costs | B14: =$F14*16/52 -> 6076.9231 | C14: =$F14*12/52 -> 4557.6923 | D14: =$F14*12/52 -> 4557.6923 | E14: =$F14*12/52 -> 4557.6923 | F14: ='FY26 RL Assumptions'!C21 -> 19750 | G14: Guidance-derived / modeled allocation | H14: Guidance midpoint allocated by fiscal weeks

Sheet Margin Reconciliation
A1: CAVA Group — FY2026 Restaurant-Level Margin Reconciliation
L2: Metric | M2: Margin | N2: Type
A3: Metric | B3: FY2025 Actual | C3: FY2026 Bottom-Up | D3: Change | E3: Guidance Low | F3: Guidance Midpoint | G3: Guidance High | H3: Variance vs Midpoint | I3: Assessment | J3: Classification | L3: FY2026 Bottom-Up | M3: =C7 -> 0.23978187 | N3: Modeled
A4: COGS % | B4: ='FY25 Actuals'!F8 -> 0.29820249 | C4: ='FY26 RL Forecast'!F7 -> 0.30219947 | D4: =C4-B4 -> 0.0039969788 | I4: =IF(ABS(D4)>ABS(D5),"Primary compression driver","Secondary driver") -> Primary compression driver | J4: Modeled assumption | L4: Guidance Midpoint | M4: =F7 -> 0.2395 | N4: Guidance
A5: Labor % | B5: ='FY25 Actuals'!F10 -> 0.2581584 | C5: ='FY26 RL Forecast'!F9 -> 0.25815697 | D5: =C5-B5 -> -1.4274179e-06 | I5: =IF(ABS(D5)>ABS(D4),"Primary compression driver","Secondary driver") -> Secondary driver | J5: Modeled assumption
A6: Occupancy / Other OPEX % | B6: ='FY26 RL Assumptions'!F13 -> 0.19986169 | C6: ='FY26 RL Forecast'!F11 -> 0.19986169 | D6: =C6-B6 -> 0 | I6: Held flat | J6: Modeled assumption
A7: Restaurant-Level Margin % | B7: 0.244 | C7: ='FY26 RL Forecast'!F13 -> 0.23978187 | D7: =C7-B7 -> -0.0042181313 | E7: 0.237 | F7: 0.2395 | G7: 0.242 | H7: =C7-F7 -> 0.00028186871 | I7: =IF(C7<E7,"Below guidance",IF(C7>G7,"Above guidance","Within guidance")) -> Within guidance | J7: Guidance reconciliation
A10: Bottom-Up vs. Management Guidance
A11: Bottom-Up Margin | B11: =C7 -> 0.23978187 | C11: Guidance Midpoint | D11: =F7 -> 0.2395
A12: Variance | B12: =H7 -> 0.00028186871 | C12: Guidance Range | D12: =TEXT(E7,"0.0%")&"–"&TEXT(G7,"0.0%") -> 23.7%–24.2%
A13: Primary Compression Driver | B13: =IF(I4="Primary compression driver","COGS","Labor") -> COGS | C13: Material Variance Flag | D13: =IF(ABS(H7)>=0.005,"Material","Not material") -> Not material
A14: Adjusted EBITDA Guidance | B14: =TEXT('FY26 RL Assumptions'!B22/1000,"$0.0")&"M–"&TEXT('FY26 RL Assumptions'!D22/1000,"$0.0")&"M" -> $176.0M–$184.0M | C14: Pre-opening Cost Guidance | D14: =TEXT('FY26 RL Assumptions'!B21/1000,"$0.0")&"M–"&TEXT('FY26 RL Assumptions'!D21/1000,"$0.0")&"M" -> $19.5M–$20.0M

Sheet Scenario Summary
A1: FY2026 Low / Base / High Scenario Summary
A3: Metric | B3: Low | C3: Base | D3: High | E3: Unit | F3: Classification | G3: Formula Basis | H3: Open Assumption | I3: Note
A4: Same Restaurant Sales Growth | B4: ='FY26 RL Assumptions'!B19 -> 0.03 | C4: ='FY26 RL Assumptions'!C19 -> 0.04 | D4: ='FY26 RL Assumptions'!D19 -> 0.05 | E4: % | F4: Guidance-derived | G4: CAVA guidance | H4: No
A5: Net New Openings | B5: ='FY26 RL Assumptions'!B18 -> 74 | C5: ='FY26 RL Assumptions'!C18 -> 75 | D5: ='FY26 RL Assumptions'!D18 -> 76 | E5: restaurants | F5: Guidance-derived | G5: CAVA guidance | H5: No
A6: FY2026 Restaurant Revenue | B6: ='FY26 RL Assumptions'!F4*(1+'FY26 RL Assumptions'!B19)+('FY26 RL Assumptions'!B18*'FY26 RL Assumptions'!F6*'FY26 RL Assumptions'!B23*'FY26 RL Assumptions'!B24) -> 1312622.9 | C6: ='FY26 RL Assumptions'!F4*(1+'FY26 RL Assumptions'!C19)+('FY26 RL Assumptions'!C18*'FY26 RL Assumptions'!F6*'FY26 RL Assumptions'!C23*'FY26 RL Assumptions'!C24) -> 1325738.1 | D6: ='FY26 RL Assumptions'!F4*(1+'FY26 RL Assumptions'!D19)+('FY26 RL Assumptions'!D18*'FY26 RL Assumptions'!F6*'FY26 RL Assumptions'!D23*'FY26 RL Assumptions'!D24) -> 1338853.2 | E6: $000s | F6: Modeled assumption | G6: FY25 base + SSS + new unit contribution | H6: Yes
A7: COGS $ | B7: =B6*'FY26 RL Forecast'!F7 -> 396673.95 | C7: =C6*'FY26 RL Forecast'!F7 -> 400637.34 | D7: =D6*'FY26 RL Forecast'!F7 -> 404600.73 | E7: $000s | F7: Modeled assumption | G7: Revenue × assumed COGS % | H7: Yes
A8: Labor $ | B8: =B6*'FY26 RL Forecast'!F9 -> 338862.76 | C8: =C6*'FY26 RL Forecast'!F9 -> 342248.52 | D8: =D6*'FY26 RL Forecast'!F9 -> 345634.29 | E8: $000s | F8: Modeled assumption | G8: Revenue × assumed labor % | H8: Yes
A9: Restaurant-Level Profit | B9: =B6*'FY26 RL Assumptions'!B20 -> 311091.63 | C9: =C6*'FY26 RL Assumptions'!C20 -> 317514.27 | D9: =D6*'FY26 RL Assumptions'!D20 -> 324002.47 | E9: $000s | F9: Guidance-derived | G9: Revenue × guided margin | H9: Revenue is modeled | I9: This figure is guidance-derived (Revenue × guided margin). The bottom-up quarterly build in FY26 RL Forecast computes Restaurant-Level Profit independently (Revenue − COGS − Labor − Occupancy/OPEX) and differs by ~$374K at Base Case (0.03pts on margin) — both figures are correct; they reflect two distinct, intentional methodologies. See Margin Reconciliation for the full variance between the two approaches.
A10: Restaurant-Level Margin | B10: ='FY26 RL Assumptions'!B20 -> 0.237 | C10: ='FY26 RL Assumptions'!C20 -> 0.2395 | D10: ='FY26 RL Assumptions'!D20 -> 0.242 | E10: % | F10: Guidance-derived | G10: CAVA guidance | H10: No
A11: Other Restaurant OPEX | B11: =B6-B7-B8-B9 -> 265994.58 | C11: =C6-C7-C8-C9 -> 265337.93 | D11: =D6-D7-D8-D9 -> 264615.71 | E11: $000s | F11: Guidance-margin plug | G11: Residual to guided margin | H11: Yes
A12: Pre-opening Costs | B12: ='FY26 RL Assumptions'!B21 -> 19500 | C12: ='FY26 RL Assumptions'!C21 -> 19750 | D12: ='FY26 RL Assumptions'!D21 -> 20000 | E12: $000s | F12: Guidance-derived | G12: CAVA guidance | H12: No
A13: Adjusted EBITDA | B13: ='FY26 RL Assumptions'!B22 -> 176000 | C13: ='FY26 RL Assumptions'!C22 -> 180000 | D13: ='FY26 RL Assumptions'!D22 -> 184000 | E13: $000s | F13: Guidance-derived | G13: CAVA guidance | H13: No

Sheet Model Guide
A1: CAVA Group — FY2026 Restaurant-Level Forecast Model Template
A3: Model purpose | B3: Quarterly FY2026 restaurant-level forecast using CAVA public guidance as the budget proxy.
A4: Units | B4: $ in thousands, except percentages, weeks, and restaurant counts.
A5: Guidance basis | B5: CAVA's original FY2026 outlook,as of the FY2025 year-end close (February 24, 2026) | C5: This analysis is intentionally scoped to information available as of CAVA's FY2025 year-end close (February 24, 2026), presenting the FY2025 performance review and FY2026 outlook as of that date. Subsequent CAVA disclosures — including Q1 FY2026 results and updated guidance issued May 19, 2026 — are outside this analysis's scope by design, consistent with treating this as a point-in-time year-end review.
A6: Blue font | B6: Hardcoded historical inputs and editable assumptions.
A7: Green font | B7: Formulas linked from another worksheet.
A8: Black font | B8: Formulas calculated within the same worksheet.
A9: Yellow fill | B9: Open assumption requiring human input or approval.
A10: Status labels | B10: Actual / Guidance-derived / Modeled assumption / Open assumption.
A11: Important limitation | B11: CAVA does not disclose FY2026 revenue, labor, COGS, G&A, or D&A guidance directly.
A12: Model guide | B12: Light green row fill: headline output — the bottom-line result the tab is building toward.
A13: Documentation | B13: Financial modeling owner | C13: Supporting source | D13: Final approver | E13: Data treatment
A14: Analysis prepared using company-disclosed guidance and filings; all modeling assumptions labeled and sourced. | B14: All forecasting figures are model-based and clearly labeled as guidance-derived or modeled assumptions where applicable. | C14: CAVA public filings / investor relations | D14: Human | E14: Figures treated as sanitized/sample unless explicitly stated otherwise.

Sheet Data Gaps
A1: Open Questions & Data Gaps
A2: Items not disclosed in public investor materials or SEC filings. Flagged for review — not filled in or estimated.
A4: Category | B4: Gap Description
A5: Granular Item-Level P&L Details | B5: No public item-level menu line items or individual item food waste yields.
A6: General Ledger (GL)-Level Expenses | B6: Fixed vs. variable utility thresholds and specific regional insurance premiums are kept internal.
A7: Unit Economics Build Specifications | B7: Exact unit build-out capex, local square-footage construction costs, and localized cash-on-cash return curve timelines are omitted from filings.
A8: RESOLVED: FY2025 D&A and G&A | B8: Verified dataset now reflected consistently across FY25 Actuals: D&A $73,661K (Q1 $20,811K; Q2 $16,815K; Q3 $17,628K; Q4 $18,407K); G&A $137,462K (Q2 corrected to $32,051K; Q4 corrected to $32,518K).
A9: RESOLVED: FY2025 COGS and Labor | B9: RESOLVED: FY2025 COGS and Labor now reflect CAVA's segment-basis reporting (matching Restaurant-Level Profit, which CAVA discloses only on a segment basis) rather than consolidated statement of operations figures used in an earlier draft. Verified: COGS $348,684K / 29.8%; Labor $301,861K / 25.8%. Source: CAVA quarterly 10-Q "CAVA Segment Results" tables and FY2025 8-K segment table (Feb 24, 2026 filing).
A10: RESOLVED: FY2025 AUV and Digital Mix | B10: AUV and Digital Mix fully populated and verified against CAVA quarterly earnings releases: AUV Q1 $2,933K; Q2 $2,939K; Q3 $2,935K; Q4 $2,934K; FY $2,930K. Digital Mix Q1 38.0%; Q2 37.3%; Q3 37.6%; Q4 38.9%; FY 37.9%.
A11: Scope Boundary | B11: Analysis reflects information available as of Feb 24, 2026 year-end close; CAVA's subsequent Q1 FY2026 results and updated guidance (May 19, 2026) are outside scope by design.

Sheet Source Register
A1: Primary Source Register
A3: Source | B3: Reporting Date | C3: Use | D3: URL
A4: CAVA Q4 and FY2024 Results | B4: 2025-02-25 | C4: Original FY2025 guidance | D4: https://investor.cava.com/news/news-details/2025/CAVA-Group-Reports-Fourth-Quarter-and-Full-Year-Fiscal-2024-Results/default.aspx
A5: CAVA Q1 2025 Results | B5: 2025-05-15 | C5: Q1 revenue, margin, Adjusted EBITDA | D5: https://investor.cava.com/news/news-details/2025/CAVA-Group-Reports-First-Quarter-2025-Results/default.aspx
A6: CAVA Q2 2025 Results | B6: 2025-08-12 | C6: Q2 revenue, margin, Adjusted EBITDA | D6: https://investor.cava.com/news/news-details/2025/CAVA-Group-Reports-Second-Quarter-2025-Results/default.aspx
A7: CAVA Q3 2025 Results | B7: 2025-11-04 | C7: Q3 revenue, margin, Adjusted EBITDA | D7: https://investor.cava.com/news/news-details/2025/CAVA-Group-Reports-Third-Quarter-2025-Results/default.aspx
A8: CAVA Q4 and FY2025 Results | B8: 2026-02-24 | C8: Q4 and FY2025 actuals | D8: https://investor.cava.com/news/news-details/2026/CAVA-Group-Reports-Fourth-Quarter-and-Full-Year-Fiscal-2025-Results/default.aspx
